{
    "棕色系": [
        {
            "名称": "槟榔棕",
            "CMYK": [
                46,
                68,
                88,
                53
            ],
            "RGB": [
                153,
                96,
                53
            ],
            "coloro": "027-44-19"
        },
        {
            "名称": "茶褐",
            "CMYK": [
                73,
                80,
                89,
                63
            ],
            "RGB": [
                47,
                30,
                20
            ],
            "coloro": "029-28-08"
        },
        {
            "名称": "丁香褐",
            "CMYK": [
                54,
                82,
                98,
                31
            ],
            "RGB": [
                113,
                55,
                31
            ],
            "coloro": "022-35-18"
        },
        {
            "名称": "沉香褐",
            "CMYK": [
                67,
                73,
                78,
                42
            ],
            "RGB": [
                87,
                65,
                61
            ],
            "coloro": "018-32-06"
        },
        {
            "名称": "桂皮棕",
            "CMYK": [
                41,
                67,
                72,
                2
            ],
            "RGB": [
                169,
                105,
                77
            ],
            "coloro": "021-51-19"
        },
        {
            "名称": "棕色",
            "CMYK": [
                41,
                67,
                72,
                2
            ],
            "RGB": [
                97,
                64,
                47
            ],
            "coloro": "021-51-19"
        },
        {
            "名称": "麂棕",
            "CMYK": [
                41,
                67,
                72,
                2
            ],
            "RGB": [
                175,
                105,
                70
            ],
            "coloro": "021-51-19"
        },
        {
            "名称": "燋茶",
            "CMYK": [
                71,
                75,
                78,
                48
            ],
            "RGB": [
                63,
                48,
                42
            ],
            "coloro": "017-23-07"
        },
        {
            "名称": "豆沙",
            "CMYK": [
                66,
                78,
                82,
                49
            ],
            "RGB": [
                72,
                45,
                36
            ],
            "coloro": "020-25-10"
        },
        {
            "名称": "酱茶褐",
            "CMYK": [
                66,
                78,
                82,
                49
            ],
            "RGB": [
                76,
                55,
                47
            ],
            "coloro": "020-25-10"
        },
        {
            "名称": "古铜",
            "CMYK": [
                67,
                75,
                78,
                42
            ],
            "RGB": [
                80,
                48,
                31
            ],
            "coloro": "020-24-05"
        },
        {
            "名称": "椒褐",
            "CMYK": [
                63,
                78,
                90,
                46
            ],
            "RGB": [
                70,
                44,
                43
            ],
            "coloro": "030-35-14"
        },
        {
            "名称": "枯竹褐",
            "CMYK": [
                24,
                43,
                55,
                0
            ],
            "RGB": [
                168,
                149,
                121
            ],
            "coloro": "034-62-06"
        },
        {
            "名称": "鹿皮褐",
            "CMYK": [
                63,
                75,
                100,
                24
            ],
            "RGB": [
                207,
                142,
                93
            ],
            "coloro": "022-57-20"
        },
        {
            "名称": "米色",
            "CMYK": [
                63,
                75,
                100,
                24
            ],
            "RGB": [
                242,
                240,
                212
            ],
            "coloro": "022-57-20"
        },
        {
            "名称": "露褐",
            "CMYK": [
                20,
                40,
                32,
                0
            ],
            "RGB": [
                214,
                186,
                164
            ],
            "coloro": "018-73-08"
        },
        {
            "名称": "墨缃",
            "CMYK": [
                80,
                80,
                65,
                65
            ],
            "RGB": [
                38,
                25,
                25
            ],
            "coloro": "012-22-06"
        },
        {
            "名称": "山鸡褐",
            "CMYK": [
                48,
                63,
                73,
                4
            ],
            "RGB": [
                152,
                106,
                76
            ],
            "coloro": "027-37-21"
        },
        {
            "名称": "石褐",
            "CMYK": [
                65,
                75,
                73,
                35
            ],
            "RGB": [
                87,
                60,
                55
            ],
            "coloro": "017-25-12"
        },
        {
            "名称": "山谷褐",
            "CMYK": [
                24,
                43,
                55,
                0
            ],
            "RGB": [
                207,
                160,
                122
            ],
            "coloro": "028-66-16"
        },
        {
            "名称": "罗汉果",
            "CMYK": [
                24,
                43,
                55,
                0
            ],
            "RGB": [
                116,
                91,
                71
            ],
            "coloro": "028-66-16"
        },
        {
            "名称": "藕褐",
            "CMYK": [
                24,
                43,
                55,
                0
            ],
            "RGB": [
                90,
                66,
                49
            ],
            "coloro": "028-66-16"
        },
        {
            "名称": "檀褐",
            "CMYK": [
                62,
                81,
                77,
                42
            ],
            "RGB": [
                86,
                48,
                45
            ],
            "coloro": "015-24-10"
        },
        {
            "名称": "棠梨褐",
            "CMYK": [
                66,
                47,
                47,
                0
            ],
            "RGB": [
                155,
                102,
                81
            ],
            "coloro": "028-49-15"
        },
        {
            "名称": "铁棕",
            "CMYK": [
                66,
                75,
                77,
                39
            ],
            "RGB": [
                57,
                34,
                34
            ],
            "coloro": "019-29-05"
        },
        {
            "名称": "笋皮棕",
            "CMYK": [
                66,
                75,
                77,
                39
            ],
            "RGB": [
                82,
                57,
                49
            ],
            "coloro": "019-29-05"
        },
        {
            "名称": "驼色",
            "CMYK": [
                56,
                65,
                75,
                13
            ],
            "RGB": [
                125,
                93,
                70
            ],
            "coloro": "028-49-15"
        },
        {
            "名称": "椰壳棕",
            "CMYK": [
                51,
                84,
                100,
                24
            ],
            "RGB": [
                128,
                57,
                25
            ],
            "coloro": "022-31-10"
        },
        {
            "名称": "橡子棕",
            "CMYK": [
                51,
                84,
                100,
                24
            ],
            "RGB": [
                142,
                71,
                59
            ],
            "coloro": "022-31-10"
        },
        {
            "名称": "迎霜褐",
            "CMYK": [
                81,
                83,
                72,
                29
            ],
            "RGB": [
                26,
                17,
                10
            ],
            "coloro": "024-21-05"
        },
        {
            "名称": "枣褐",
            "CMYK": [
                60,
                81,
                72,
                31
            ],
            "RGB": [
                102,
                56,
                57
            ],
            "coloro": "010-27-15"
        },
        {
            "名称": "赭石",
            "CMYK": [
                29,
                74,
                76,
                0
            ],
            "RGB": [
                195,
                96,
                66
            ],
            "coloro": "017-43-20"
        },
        {
            "名称": "砖褐",
            "CMYK": [
                56,
                76,
                75,
                23
            ],
            "RGB": [
                116,
                69,
                59
            ],
            "coloro": "015-36-17"
        },
        {
            "名称": "紫檀",
            "CMYK": [
                61,
                92,
                79,
                50
            ],
            "RGB": [
                79,
                26,
                34
            ],
            "coloro": "010-24-21"
        }
    ]
}